{
	"info": {
		"_postman_id": "0b5cbaf2-a51d-4b6c-b640-f25285160633",
		"name": "API-4.1",
		"schema": "https://schema.getpostman.com/json/collection/v2.1.0/collection.json",
		"_exporter_id": "20586342"
	},
	"item": [
		{
			"name": "Register",
			"item": [
				{
					"name": "Valid Data",
					"event": [
						{
							"listen": "test",
							"script": {
								"exec": [
									"// Test 1: Проверка статус кода",
									"pm.test(\"Status code is 201 Created\", function () {",
									"    pm.response.to.have.status(201);",
									"});",
									"",
									"// Test 2: Время ответа меньше 2000ms",
									"pm.test(\"Response time is less than 2000ms\", function () {",
									"    pm.expect(pm.response.responseTime).to.be.below(2000);",
									"});",
									"",
									"// Test 3: Проверка Content-Type",
									"pm.test(\"Content-Type is present\", function () {",
									"    pm.response.to.have.header(\"Content-Type\");",
									"});",
									"",
									"// Сохраняем login и email в переменные окружения для следующих тестов",
									"var requestBody = JSON.parse(pm.request.body.raw);",
									"pm.environment.set(\"randomLogin\", requestBody.login);",
									"pm.environment.set(\"randomEmail\", requestBody.email);",
									"",
									"console.log(\"Created user:\", requestBody.login);"
								],
								"type": "text/javascript",
								"packages": {},
								"requests": {}
							}
						}
					],
					"request": {
						"method": "POST",
						"header": [
							{
								"key": "Content-Type",
								"value": "application/json",
								"type": "text"
							}
						],
						"body": {
							"mode": "raw",
							"raw": "{\n  \"login\": \"testuser_{{$timestamp}}\",\n  \"email\": \"testuser{{$timestamp}}@test.com\",\n  \"password\": \"Test123!\",\n  \"langKey\": \"en\"\n}",
							"options": {
								"raw": {
									"language": "json"
								}
							}
						},
						"url": {
							"raw": "{{baseUrl}}/api/register",
							"host": [
								"{{baseUrl}}"
							],
							"path": [
								"api",
								"register"
							]
						}
					},
					"response": []
				},
				{
					"name": "Existing Username",
					"event": [
						{
							"listen": "test",
							"script": {
								"exec": [
									"// Test 1: Проверка статус кода 400",
									"pm.test(\"Status code is 400 Bad Request\", function () {",
									"    pm.response.to.have.status(400);",
									"});",
									"",
									"// Test 2: Проверка наличия ошибки в ответе",
									"pm.test(\"Response contains error message\", function () {",
									"    var jsonData = pm.response.json();",
									"    pm.expect(jsonData).to.have.property('title');",
									"});",
									"",
									"// Test 3: Время ответа меньше 2000ms",
									"pm.test(\"Response time is less than 2000ms\", function () {",
									"    pm.expect(pm.response.responseTime).to.be.below(2000);",
									"});"
								],
								"type": "text/javascript",
								"packages": {},
								"requests": {}
							}
						}
					],
					"request": {
						"method": "POST",
						"header": [
							{
								"key": "Content-Type",
								"value": "application/json",
								"type": "text"
							}
						],
						"body": {
							"mode": "raw",
							"raw": "{\n  \"login\": \"admin_automation\",\n  \"email\": \"newemail{{$timestamp}}@test.com\",\n  \"password\": \"Test123!\",\n  \"langKey\": \"en\"\n}",
							"options": {
								"raw": {
									"language": "json"
								}
							}
						},
						"url": {
							"raw": "{{baseUrl}}/api/register",
							"host": [
								"{{baseUrl}}"
							],
							"path": [
								"api",
								"register"
							]
						}
					},
					"response": []
				}
			]
		},
		{
			"name": "Login",
			"item": [
				{
					"name": "Valid Credentials",
					"event": [
						{
							"listen": "test",
							"script": {
								"exec": [
									"// Test 1: Проверка статус кода 200",
									"pm.test(\"Status code is 200 OK\", function () {",
									"    pm.response.to.have.status(200);",
									"});",
									"",
									"// Test 2: Проверка наличия JWT токена в ответе",
									"pm.test(\"Response contains JWT token\", function () {",
									"    var jsonData = pm.response.json();",
									"    pm.expect(jsonData).to.have.property('id_token');",
									"    pm.expect(jsonData.id_token).to.be.a('string');",
									"    pm.expect(jsonData.id_token.length).to.be.above(10);",
									"    ",
									"    // Сохраняем токен в переменную окружения",
									"    pm.environment.set(\"authToken\", jsonData.id_token);",
									"});",
									"",
									"// Test 3: Время ответа меньше 2000ms",
									"pm.test(\"Response time is less than 2000ms\", function () {",
									"    pm.expect(pm.response.responseTime).to.be.below(2000);",
									"});",
									"",
									"console.log(\"JWT Token saved to environment\");"
								],
								"type": "text/javascript",
								"packages": {},
								"requests": {}
							}
						}
					],
					"request": {
						"method": "POST",
						"header": [
							{
								"key": "Content-Type",
								"value": "application/json",
								"type": "text"
							}
						],
						"body": {
							"mode": "raw",
							"raw": "{\n  \"username\": \"admin_automation\",\n  \"password\": \"admin_automation\",\n  \"rememberMe\": false\n}",
							"options": {
								"raw": {
									"language": "json"
								}
							}
						},
						"url": {
							"raw": "{{baseUrl}}/api/authenticate",
							"host": [
								"{{baseUrl}}"
							],
							"path": [
								"api",
								"authenticate"
							]
						}
					},
					"response": []
				},
				{
					"name": "Wrong Password",
					"event": [
						{
							"listen": "test",
							"script": {
								"exec": [
									"// Test 1: Проверка статус кода 401",
									"pm.test(\"Status code is 401 Unauthorized\", function () {",
									"    pm.response.to.have.status(401);",
									"});",
									"",
									"// Test 2: Проверка отсутствия токена",
									"pm.test(\"Response does not contain token\", function () {",
									"    var jsonData = pm.response.json();",
									"    pm.expect(jsonData).to.not.have.property('id_token');",
									"});",
									"",
									"// Test 3: Время ответа меньше 2000ms",
									"pm.test(\"Response time is less than 2000ms\", function () {",
									"    pm.expect(pm.response.responseTime).to.be.below(2000);",
									"});"
								],
								"type": "text/javascript",
								"packages": {},
								"requests": {}
							}
						}
					],
					"request": {
						"method": "POST",
						"header": [
							{
								"key": "Content-Type",
								"value": "application/json",
								"type": "text"
							}
						],
						"body": {
							"mode": "raw",
							"raw": "{\n  \"username\": \"admin_automation\",\n  \"password\": \"wrongpassword123\",\n  \"rememberMe\": false\n}",
							"options": {
								"raw": {
									"language": "json"
								}
							}
						},
						"url": {
							"raw": "{{baseUrl}}/api/authenticate",
							"host": [
								"{{baseUrl}}"
							],
							"path": [
								"api",
								"authenticate"
							]
						}
					},
					"response": []
				},
				{
					"name": "Get Account Info",
					"event": [
						{
							"listen": "test",
							"script": {
								"exec": [
									"// Test 1: Проверка статус кода 200",
									"pm.test(\"Status code is 200 OK\", function () {",
									"    pm.response.to.have.status(200);",
									"});",
									"",
									"// Test 2: Проверка структуры ответа",
									"pm.test(\"Response contains user data\", function () {",
									"    var jsonData = pm.response.json();",
									"    pm.expect(jsonData).to.have.property('login');",
									"    pm.expect(jsonData).to.have.property('email');",
									"    pm.expect(jsonData).to.have.property('activated');",
									"});",
									"",
									"// Test 3: Проверка, что пользователь активирован",
									"pm.test(\"User is activated\", function () {",
									"    var jsonData = pm.response.json();",
									"    pm.expect(jsonData.activated).to.be.true;",
									"});",
									"",
									"// Test 4: Время ответа меньше 2000ms",
									"pm.test(\"Response time is less than 2000ms\", function () {",
									"    pm.expect(pm.response.responseTime).to.be.below(2000);",
									"});",
									"",
									"console.log(\"User info:\", pm.response.json().login);"
								],
								"type": "text/javascript",
								"packages": {},
								"requests": {}
							}
						}
					],
					"request": {
						"auth": {
							"type": "bearer",
							"bearer": [
								{
									"key": "token",
									"value": "{{authToken}}",
									"type": "string"
								}
							]
						},
						"method": "GET",
						"header": [],
						"url": {
							"raw": "{{baseUrl}}/api/account",
							"host": [
								"{{baseUrl}}"
							],
							"path": [
								"api",
								"account"
							]
						}
					},
					"response": []
				}
			]
		},
		{
			"name": "Tasks",
			"item": [
				{
					"name": "Create Task",
					"event": [
						{
							"listen": "test",
							"script": {
								"exec": [
									"// Test 1: Статус код 201",
									"pm.test(\"Status code is 201 Created\", function () {",
									"    pm.response.to.have.status(201);",
									"});",
									"",
									"// Test 2: Response содержит ID",
									"pm.test(\"Response contains task ID\", function () {",
									"    var jsonData = pm.response.json();",
									"    pm.expect(jsonData).to.have.property('id');",
									"    pm.expect(jsonData.id).to.be.above(0);",
									"    ",
									"    // Сохраняем ID для следующих запросов",
									"    pm.environment.set(\"taskId\", jsonData.id);",
									"});",
									"",
									"// Test 3: Проверка всех полей",
									"pm.test(\"Response contains all task fields\", function () {",
									"    var jsonData = pm.response.json();",
									"    pm.expect(jsonData).to.have.property('text');",
									"    pm.expect(jsonData).to.have.property('answer');",
									"    pm.expect(jsonData).to.have.property('title');",
									"});",
									"",
									"// Test 4: Время ответа",
									"pm.test(\"Response time is acceptable\", function () {",
									"    pm.expect(pm.response.responseTime).to.be.below(2000);",
									"});"
								],
								"type": "text/javascript",
								"packages": {},
								"requests": {}
							}
						}
					],
					"request": {
						"auth": {
							"type": "bearer",
							"bearer": [
								{
									"key": "token",
									"value": "{{authToken}}",
									"type": "string"
								}
							]
						},
						"method": "POST",
						"header": [
							{
								"key": "Content-Type",
								"value": "application/json",
								"type": "text"
							}
						],
						"body": {
							"mode": "raw",
							"raw": "{\n  \"text\": \"Test task\",\n  \"answer\": \"Test answer\",\n  \"title\": \"Test_{{$timestamp}}\"\n}",
							"options": {
								"raw": {
									"language": "json"
								}
							}
						},
						"url": {
							"raw": "{{baseUrl}}/api/tasks",
							"host": [
								"{{baseUrl}}"
							],
							"path": [
								"api",
								"tasks"
							]
						}
					},
					"response": []
				},
				{
					"name": "Get Task by ID",
					"event": [
						{
							"listen": "test",
							"script": {
								"exec": [
									"// Test 1: Статус код 200",
									"pm.test(\"Status code is 200 OK\", function () {",
									"    pm.response.to.have.status(200);",
									"});",
									"",
									"// Test 2: ID совпадает с запрошенным",
									"pm.test(\"Task ID matches requested ID\", function () {",
									"    var jsonData = pm.response.json();",
									"    var requestedId = pm.environment.get(\"taskId\");",
									"    pm.expect(jsonData.id).to.eql(Number(requestedId));",
									"});",
									"",
									"// Test 3: Все поля присутствуют",
									"pm.test(\"Response contains all fields\", function () {",
									"    var jsonData = pm.response.json();",
									"    pm.expect(jsonData).to.have.property('id');",
									"    pm.expect(jsonData).to.have.property('text');",
									"    pm.expect(jsonData).to.have.property('answer');",
									"    pm.expect(jsonData).to.have.property('title');",
									"});"
								],
								"type": "text/javascript",
								"packages": {},
								"requests": {}
							}
						}
					],
					"protocolProfileBehavior": {
						"disableBodyPruning": true
					},
					"request": {
						"auth": {
							"type": "bearer",
							"bearer": [
								{
									"key": "token",
									"value": "{{authToken}}",
									"type": "string"
								}
							]
						},
						"method": "GET",
						"header": [],
						"body": {
							"mode": "raw",
							"raw": "",
							"options": {
								"raw": {
									"language": "json"
								}
							}
						},
						"url": {
							"raw": "{{baseUrl}}/api/tasks/{{taskId}}",
							"host": [
								"{{baseUrl}}"
							],
							"path": [
								"api",
								"tasks",
								"{{taskId}}"
							]
						}
					},
					"response": []
				},
				{
					"name": "Update Task",
					"event": [
						{
							"listen": "test",
							"script": {
								"exec": [
									"// Test 1: Статус код 200",
									"pm.test(\"Status code is 200 OK\", function () {",
									"    pm.response.to.have.status(200);",
									"});",
									"",
									"// Test 2: Данные обновились",
									"pm.test(\"Task text was updated\", function () {",
									"    var jsonData = pm.response.json();",
									"    pm.expect(jsonData.text).to.eql(\"Updated task text\");",
									"});",
									"",
									"// Test 3: Answer обновился",
									"pm.test(\"Task answer was updated\", function () {",
									"    var jsonData = pm.response.json();",
									"    pm.expect(jsonData.answer).to.eql(\"Updated answer\");",
									"});",
									"",
									"// Test 4: ID остался тем же",
									"pm.test(\"Task ID unchanged\", function () {",
									"    var jsonData = pm.response.json();",
									"    var originalId = pm.environment.get(\"taskId\");",
									"    pm.expect(jsonData.id).to.eql(Number(originalId));",
									"});"
								],
								"type": "text/javascript",
								"packages": {},
								"requests": {}
							}
						}
					],
					"request": {
						"auth": {
							"type": "bearer",
							"bearer": [
								{
									"key": "token",
									"value": "{{authToken}}",
									"type": "string"
								}
							]
						},
						"method": "PUT",
						"header": [],
						"body": {
							"mode": "raw",
							"raw": "{\n    \"id\": {{taskId}},\n    \"text\": \"Updated task text\",\n    \"answer\": \"Updated answer\",\n    \"title\": \"Updated_{{$timestamp}}\"\n}",
							"options": {
								"raw": {
									"language": "json"
								}
							}
						},
						"url": {
							"raw": "{{baseUrl}}/api/tasks/{{taskId}}",
							"host": [
								"{{baseUrl}}"
							],
							"path": [
								"api",
								"tasks",
								"{{taskId}}"
							]
						}
					},
					"response": []
				},
				{
					"name": "New Request",
					"event": [
						{
							"listen": "test",
							"script": {
								"exec": [
									"// Test 1: Статус код 204 No Content",
									"pm.test(\"Status code is 204 No Content\", function () {",
									"    pm.response.to.have.status(204);",
									"});",
									"",
									"// Test 2: Body пустой (для DELETE это норма)",
									"pm.test(\"Response body is empty\", function () {",
									"    pm.expect(pm.response.text()).to.be.empty;",
									"});"
								],
								"type": "text/javascript",
								"packages": {},
								"requests": {}
							}
						}
					],
					"request": {
						"auth": {
							"type": "bearer",
							"bearer": [
								{
									"key": "token",
									"value": "{{authToken}}",
									"type": "string"
								}
							]
						},
						"method": "DELETE",
						"header": [],
						"url": {
							"raw": "{{baseUrl}}/api/tasks/{{taskId}}",
							"host": [
								"{{baseUrl}}"
							],
							"path": [
								"api",
								"tasks",
								"{{taskId}}"
							]
						}
					},
					"response": []
				},
				{
					"name": "Get Deleted Task - 404",
					"event": [
						{
							"listen": "test",
							"script": {
								"exec": [
									"// Test 1: Статус код 404 Not Found",
									"pm.test(\"Status code is 404 Not Found\", function () {",
									"    pm.response.to.have.status(404);",
									"});",
									"",
									"// Test 2: Задача не найдена",
									"pm.test(\"Task no longer exists\", function () {",
									"    pm.expect(pm.response.code).to.eql(404);",
									"});"
								],
								"type": "text/javascript",
								"packages": {},
								"requests": {}
							}
						}
					],
					"request": {
						"auth": {
							"type": "bearer",
							"bearer": [
								{
									"key": "token",
									"value": "{{authToken}}",
									"type": "string"
								}
							]
						},
						"method": "GET",
						"header": [],
						"url": {
							"raw": "{{baseUrl}}/api/tasks/{{taskId}}",
							"host": [
								"{{baseUrl}}"
							],
							"path": [
								"api",
								"tasks",
								"{{taskId}}"
							]
						}
					},
					"response": []
				}
			]
		}
	]
}